clu/__init__.py
clu/__main__.py
clu/__version__.py
clu/abstract.py
clu/all.py
clu/application.py
clu/csv.py
clu/dicts.py
clu/dispatch.py
clu/enums.py
clu/exporting.py
clu/extending.py
clu/keyvalue.py
clu/mathematics.py
clu/naming.py
clu/predicates.py
clu/repr.py
clu/sanitizer.py
clu/stdio.py
clu/trie.py
clu/typology.py
clu/api/__init__.py
clu/api/__main__.py
clu/compilation/__init__.py
clu/compilation/compiledb.py
clu/compilation/macros.py
clu/config/__init__.py
clu/config/abc.py
clu/config/codecs.py
clu/config/env.py
clu/config/filebase.py
clu/config/keymap.py
clu/config/keymaputils.py
clu/config/keymapview.py
clu/config/ns.py
clu/config/proxy.py
clu/config/formats/__init__.py
clu/config/formats/jsonfile.py
clu/config/formats/picklefile.py
clu/config/formats/tomlfile.py
clu/config/formats/yamlfile.py
clu/config/legacy/__init__.py
clu/config/legacy/base.py
clu/config/legacy/fieldtypes.py
clu/config/legacy/settings.py
clu/constants/__init__.py
clu/constants/__main__.py
clu/constants/consts.py
clu/constants/data.py
clu/constants/enums.py
clu/constants/exceptions.py
clu/constants/polyfills.py
clu/fs/__init__.py
clu/fs/abc.py
clu/fs/appdirectories.py
clu/fs/filesystem.py
clu/fs/misc.py
clu/fs/pypath.py
clu/fs/sourcetree.py
clu/importing/__init__.py
clu/importing/__main__.py
clu/importing/base.py
clu/importing/proxy.py
clu/repl/__init__.py
clu/repl/ansi.py
clu/repl/banners.py
clu/repl/columnize.py
clu/repl/modules.py
clu/repl/cli/__init__.py
clu/repl/cli/ansidocs.py
clu/repl/cli/boilerplate.py
clu/repl/cli/boilerplate_copy.py
clu/repl/cli/print_version.py
clu/scripts/.gitignore
clu/scripts/README.md
clu/scripts/__init__.py
clu/scripts/ansicolors.py
clu/scripts/boilerplate.py
clu/scripts/dictroast.py
clu/scripts/prediversus.py
clu/scripts/repl.py
clu/scripts/treeline.py
clu/scripts/legacy/forkumask.py
clu/scripts/legacy/repl-bpython.py
clu/scripts/legacy/repl-ipython.py
clu/scripts/legacy/repl-ptpython.py
clu/scripts/legacy/repl-pyzo.py
clu/scripts/legacy/xdg-runtime.py
python_clu-0.12.20.dist-info/licenses/LICENSE.txt
python_clu-0.12.20.dist-info/METADATA
python_clu-0.12.20.dist-info/WHEEL
python_clu-0.12.20.dist-info/entry_points.txt
python_clu-0.12.20.dist-info/top_level.txt
python_clu-0.12.20.dist-info/zip-safe
python_clu-0.12.20.dist-info/RECORD
