Metadata-Version: 2.4
Name: python-clu
Version: 0.12.20
Summary: Python-CLU: Common Lightweight Utilities
Home-page: https://github.com/fish2000/clu
Download-URL: https://github.com/fish2000/clu/zipball/master
Author: Alexander Böhn
Author-email: Alexander Böhn <fish2000@gmail.com>
Maintainer-email: Alexander Böhn <fish2000@gmail.com>
License-Expression: LicenseRef-CLU-MIT
Project-URL: Homepage, https://github.com/fish2000/CLU
Project-URL: Repository, https://github.com/fish2000/CLU
Project-URL: Documentation, https://github.com/fish2000/CLU/blob/master/README.md
Project-URL: Source, https://github.com/fish2000/CLU
Project-URL: Tracker, https://github.com/fish2000/CLU/issues
Project-URL: Changelog, https://github.com/fish2000/CLU/blob/master/CHANGELOG.md
Project-URL: Download, https://pypi.org/project/python-clu/
Project-URL: License, https://github.com/fish2000/CLU/blob/master/LICENSE.txt
Keywords: testing,command,command-line,utilities,modules,REPL,tools
Platform: any
Classifier: Development Status :: 5 - Production/Stable
Classifier: Framework :: Pytest
Classifier: Intended Audience :: Developers
Classifier: Topic :: Software Development
Classifier: Topic :: Software Development :: Testing
Classifier: Topic :: Utilities
Classifier: Operating System :: MacOS
Classifier: Operating System :: OS Independent
Classifier: Operating System :: POSIX
Classifier: Operating System :: Unix
Classifier: Programming Language :: Python
Classifier: Programming Language :: Python :: 3
Classifier: Programming Language :: Python :: 3.10
Classifier: Programming Language :: Python :: Implementation :: CPython
Classifier: Programming Language :: Python :: Implementation :: PyPy
License-File: LICENSE.txt
Requires-Dist: build>=1.2.2
Requires-Dist: colorama>=0.4.0
Requires-Dist: dataclasses>=0.6; python_version < "3.7"
Requires-Dist: dbx-stopwatch>=1.6
Requires-Dist: enum34>=1.1.0; python_version < "3.4"
Requires-Dist: humanize>=1.0.0
Requires-Dist: importlib-metadata>=1.4.0; python_version < "3.8"
Requires-Dist: mock>=4.0.0
Requires-Dist: multidict>=4.7.0
Requires-Dist: packaging
Requires-Dist: pout>=0.8.13
Requires-Dist: pygments>=2.0.0
Requires-Dist: PyYAML>=5.3.0
Requires-Dist: redis>=3.4.0
Requires-Dist: setuptools>=30.0.0
Requires-Dist: toml>=0.10.0
Requires-Dist: tomli>=2.2.0
Requires-Dist: tomli_w>=1.2.0
Requires-Dist: wheel>=0.34.0
Requires-Dist: zict>=0.1.2
Provides-Extra: all
Requires-Dist: numpy>=1.17.0; extra == "all"
Requires-Dist: Pillow>=7.1.0; extra == "all"
Requires-Dist: pytest>=5.4.0; extra == "all"
Requires-Dist: xerox>=0.4.0; extra == "all"
Requires-Dist: zipp>=2.0.0; extra == "all"
Dynamic: author
Dynamic: download-url
Dynamic: home-page
Dynamic: license-file
Dynamic: platform
